axon_synthesis/__init__.py
axon_synthesis/atlas.py
axon_synthesis/base_path_builder.py
axon_synthesis/constants.py
axon_synthesis/typing.py
axon_synthesis/utils.py
axon_synthesis/version.py
axon_synthesis/white_matter_recipe.py
axon_synthesis/cli/__init__.py
axon_synthesis/cli/common.py
axon_synthesis/cli/input_creation.py
axon_synthesis/cli/scripts.py
axon_synthesis/cli/synthesis.py
axon_synthesis/cli/utils.py
axon_synthesis/cli/validation.py
axon_synthesis/data/tuft_distributions.json
axon_synthesis/data/tuft_parameters.json
axon_synthesis/inputs/__init__.py
axon_synthesis/inputs/create.py
axon_synthesis/inputs/pop_neuron_numbers.py
axon_synthesis/inputs/trunk_properties.py
axon_synthesis/inputs/clustering/__init__.py
axon_synthesis/inputs/clustering/extract_terminals.py
axon_synthesis/inputs/clustering/from_barcodes.py
axon_synthesis/inputs/clustering/from_brain_regions.py
axon_synthesis/inputs/clustering/from_sphere_parents.py
axon_synthesis/inputs/clustering/from_spheres.py
axon_synthesis/inputs/clustering/plot.py
axon_synthesis/inputs/clustering/utils.py
axon_synthesis/synthesis/__init__.py
axon_synthesis/synthesis/add_tufts.py
axon_synthesis/synthesis/outputs.py
axon_synthesis/synthesis/plot.py
axon_synthesis/synthesis/source_points.py
axon_synthesis/synthesis/target_points.py
axon_synthesis/synthesis/tuft_properties.py
axon_synthesis/synthesis/main_trunk/__init__.py
axon_synthesis/synthesis/main_trunk/post_process.py
axon_synthesis/synthesis/main_trunk/steiner_morphology.py
axon_synthesis/synthesis/main_trunk/steiner_tree.py
axon_synthesis/synthesis/main_trunk/create_graph/__init__.py
axon_synthesis/synthesis/main_trunk/create_graph/plot.py
axon_synthesis/synthesis/main_trunk/create_graph/utils.py
axon_synthesis/validation/__init__.py
axon_synthesis/validation/atlas_utils.py
axon_synthesis/validation/mimic.py
axon_synthesis/validation/projection_intensity.py
axon_synthesis/validation/statistics.py
axon_synthesis/validation/utils.py
axon_synthesis-0.1.10.dist-info/AUTHORS.md
axon_synthesis-0.1.10.dist-info/LICENSE.txt
axon_synthesis-0.1.10.dist-info/METADATA
axon_synthesis-0.1.10.dist-info/WHEEL
axon_synthesis-0.1.10.dist-info/entry_points.txt
axon_synthesis-0.1.10.dist-info/top_level.txt
axon_synthesis-0.1.10.dist-info/RECORD
